odoo10_addon_base_phone_popup-10.0.1.0.0.99.dev6-py3.8-nspkg.pth
odoo/addons/base_phone_popup/README.rst
odoo/addons/base_phone_popup/__init__.py
odoo/addons/base_phone_popup/__manifest__.py
odoo/addons/base_phone_popup/i18n/base_phone_popup.pot
odoo/addons/base_phone_popup/i18n/fr.po
odoo/addons/base_phone_popup/i18n/sl.po
odoo/addons/base_phone_popup/models/__init__.py
odoo/addons/base_phone_popup/models/phone_common.py
odoo/addons/base_phone_popup/readme/CONTRIBUTORS.rst
odoo/addons/base_phone_popup/readme/DESCRIPTION.rst
odoo/addons/base_phone_popup/readme/USAGE.rst
odoo/addons/base_phone_popup/static/description/icon.png
odoo/addons/base_phone_popup/static/description/index.html
odoo10_addon_base_phone_popup-10.0.1.0.0.99.dev6.dist-info/METADATA
odoo10_addon_base_phone_popup-10.0.1.0.0.99.dev6.dist-info/WHEEL
odoo10_addon_base_phone_popup-10.0.1.0.0.99.dev6.dist-info/namespace_packages.txt
odoo10_addon_base_phone_popup-10.0.1.0.0.99.dev6.dist-info/top_level.txt
odoo10_addon_base_phone_popup-10.0.1.0.0.99.dev6.dist-info/RECORD
